scloop-0.1.23.dist-info/RECORD
scloop-0.1.23.dist-info/WHEEL
scloop-0.1.23.dist-info/top_level.txt
scloop-0.1.23.dist-info/METADATA
scloop-0.1.23.dist-info/licenses/LICENSE
scloop/__init__.py
scloop/py.typed
scloop/matching/cross_dataset.py
scloop/matching/__init__.py
scloop/matching/mlp.py
scloop/matching/nf.py
scloop/matching/data_modules.py
scloop/tools/_cross_match.py
scloop/tools/__init__.py
scloop/tools/_loops.py
scloop/io/__init__.py
scloop/utils/logging.py
scloop/utils/pvalues.py
scloop/utils/__init__.py
scloop/utils/distance_metrics/frechet_py.py
scloop/utils/distance_metrics/frechet.pyx
scloop/utils/distance_metrics/frechet.cpython-312-darwin.so
scloop/utils/distance_metrics/__init__.py
scloop/utils/distance_metrics/frechet.cpp
scloop/utils/distance_metrics/discrete-frechet-distance/Frechet.h
scloop/utils/distance_metrics/discrete-frechet-distance/Frechet.cpp
scloop/utils/linear_algebra_gf2/gf2toolkit_wrapper.cpp
scloop/utils/linear_algebra_gf2/__init__.py
scloop/utils/linear_algebra_gf2/gf2toolkit_lib.pyx
scloop/utils/linear_algebra_gf2/gf2toolkit_lib.cpp
scloop/utils/linear_algebra_gf2/gf2toolkit_wrapper.hpp
scloop/utils/linear_algebra_gf2/libm4ri.a
scloop/utils/linear_algebra_gf2/m4ri_lib.pyx
scloop/utils/linear_algebra_gf2/m4ri_lib.c
scloop/utils/linear_algebra_gf2/m4ri_lib.cpython-312-darwin.so
scloop/utils/linear_algebra_gf2/GF2toolkit/srcs/GF2toolkit_LU.hh
scloop/utils/linear_algebra_gf2/GF2toolkit/srcs/GF2toolkit_4RussianMacros.hh
scloop/utils/linear_algebra_gf2/GF2toolkit/srcs/GF2toolkit_MatrixMult.hh
scloop/utils/linear_algebra_gf2/GF2toolkit/srcs/GF2toolkit_m4ri.hh
scloop/utils/linear_algebra_gf2/GF2toolkit/srcs/GF2toolkit_Strassen.hh
scloop/utils/linear_algebra_gf2/GF2toolkit/srcs/GF2toolkit_Matrix.hh
scloop/utils/linear_algebra_gf2/GF2toolkit/srcs/GF2toolkit_MatrixLower.hh
scloop/utils/linear_algebra_gf2/GF2toolkit/srcs/GF2toolkit_InvertBlock.hh
scloop/utils/linear_algebra_gf2/GF2toolkit/srcs/GF2toolkit_4Russian.hh
scloop/utils/linear_algebra_gf2/GF2toolkit/srcs/Random.hh
scloop/utils/linear_algebra_gf2/GF2toolkit/srcs/GF2toolkit_popCounts.hh
