Metadata-Version: 2.4
Name: scloop
Version: 0.1.23
Summary: single-cell loop analysis
Author-email: "Zhiyuan(Stan) Yu and Idse Heemskerk" <zyyu@umich.edu>
Project-URL: Issues, https://github.com/stanfish06/scloop/issues
Project-URL: Repository, https://github.com/stanfish06/scloop.git
Classifier: Programming Language :: Python :: 3 :: Only
Classifier: Programming Language :: Python :: 3.12
Requires-Python: >=3.12
License-File: LICENSE
Requires-Dist: cython>=3.0.12
Requires-Dist: glasbey==0.3
Requires-Dist: igraph>=0.11
Requires-Dist: loguru==0.7.3
Requires-Dist: numba>=0.62.1
Requires-Dist: numpy<2
Requires-Dist: pandas
Requires-Dist: pip>=25.2
Requires-Dist: pydantic>=2.11.4
Requires-Dist: pygam>=0.12
Requires-Dist: pynndescent>=0.5.13
Requires-Dist: pytest>=8.4
Requires-Dist: rich==14.2
Requires-Dist: scanpy[leiden]>=1.11.2
Requires-Dist: scikit-misc>=0.5.2
Requires-Dist: statsmodels==0.14.4
Requires-Dist: tensorflow>=2.18.1
Requires-Dist: torch
Requires-Dist: torchdyn>=1.0.6
Requires-Dist: torchvision
Requires-Dist: tqdm-joblib>=0.0.5
Requires-Dist: umap-learn>=0.5.7
Dynamic: license-file
